fmugym/__init__.py
fmugym/fmugym.py
fmugym/fmugym_config.py
fmugym-0.2.0.dist-info/LICENSE
fmugym-0.2.0.dist-info/METADATA
fmugym-0.2.0.dist-info/WHEEL
fmugym-0.2.0.dist-info/RECORD
