Metadata-Version: 2.3
Name: fmugym
Version: 0.2.0
Summary: Interface to connect Reinforcement Learning libraries to Functional Mock-up Units for control under uncertainties
License: MIT
Author: Konstantin Wrede
Author-email: konstantin.wrede@eas.iis.fraunhofer.de
Requires-Python: >=3.10,<4.0
Classifier: License :: OSI Approved :: MIT License
Classifier: Programming Language :: Python :: 3
Classifier: Programming Language :: Python :: 3.10
Classifier: Programming Language :: Python :: 3.11
Classifier: Programming Language :: Python :: 3.12
Classifier: Programming Language :: Python :: 3.13
Requires-Dist: fmpy (>=0.3.20,<0.4.0)
Requires-Dist: gymnasium (>=0.29.1,<0.30.0)
Requires-Dist: matplotlib (>=3.8.3,<4.0.0)
Requires-Dist: numpy
Project-URL: Repository, https://github.com/Fraunhofer-IIS/fmugym
